json_2_postgres/__init__.py
json_2_postgres/flk.py
json_2_postgres/table_to_dict.py
json_2_postgres/table_to_json.py
json_2_postgres-0.3.0.dist-info/METADATA
json_2_postgres-0.3.0.dist-info/WHEEL
json_2_postgres-0.3.0.dist-info/top_level.txt
json_2_postgres-0.3.0.dist-info/RECORD
