Metadata-Version: 2.4
Name: json_2_postgres
Version: 0.3.0
Summary: Набор утилит для конвертации таблиц postges в json формат и обратно
Author-email: Denis Maslennиков <ktotom7@yandex.ru>
Requires-Python: >=3.7
Requires-Dist: jsonschema>=4.17.3
Requires-Dist: psycopg2-binary>=2.9.9
